harpy/__init__.py
harpy/har_file.py
harpy/har_file_io.py
harpy/header_array.py
harpy/tests/__init__.py
harpy/tests/test_har_file.py
harpy/tests/test_har_file_io.py
harpy/tests/test_harpy.py
harpy/tests/test_header_array.py
harpy/tests/testdata/Mdatnew7.har
harpy/tests/testdata/__init__.py
harpy/tests/testdata/setsnew7.har
harpy/tests/testdata/test.har
harpy/tests/testdata/test_read.har
harpy3-0.3.1.dist-info/DESCRIPTION.rst
harpy3-0.3.1.dist-info/METADATA
harpy3-0.3.1.dist-info/RECORD
harpy3-0.3.1.dist-info/WHEEL
harpy3-0.3.1.dist-info/metadata.json
harpy3-0.3.1.dist-info/top_level.txt
