Metadata-Version: 2.0
Name: harpy3
Version: 0.3.1
Summary: Library for reading/modifying/writing header-array (HAR) files.
Home-page: https://github.com/GEMPACKsoftware/HARPY
Author: Lyle Collins
Author-email: Lyle.Collins@csiro.au
License: GPLv3
Platform: UNKNOWN
Requires-Python: >=3.4
Requires-Dist: numpy
